tracking_analyzer/__init__.py
tracking_analyzer/admin.py
tracking_analyzer/apps.py
tracking_analyzer/conf.py
tracking_analyzer/manager.py
tracking_analyzer/models.py
tracking_analyzer/utils.py
tracking_analyzer/management/__init__.py
tracking_analyzer/management/commands/__init__.py
tracking_analyzer/management/commands/install_geoip_dataset.py
tracking_analyzer/migrations/0001_initial.py
tracking_analyzer/migrations/0002_auto_20160719_2212.py
tracking_analyzer/migrations/__init__.py
tracking_analyzer/static/admin/css/d3-tip.css
tracking_analyzer/static/admin/css/main.css
tracking_analyzer/static/admin/js/devices_stats.js
tracking_analyzer/static/admin/js/requests_graph.js
tracking_analyzer/static/admin/js/world_map.js
tracking_analyzer/static/admin/js/vendor/d3/LICENSE
tracking_analyzer/static/admin/js/vendor/d3/d3.min.js
tracking_analyzer/static/admin/js/vendor/d3-tip/LICENSE
tracking_analyzer/static/admin/js/vendor/d3-tip/d3-tip.min.js
tracking_analyzer/static/admin/js/vendor/datamaps/LICENSE
tracking_analyzer/static/admin/js/vendor/datamaps/datamaps.world.min.js
tracking_analyzer/static/admin/js/vendor/topojson/LICENSE
tracking_analyzer/static/admin/js/vendor/topojson/topojson.min.js
tracking_analyzer/templates/admin/tracking_analyzer/tracker/change_list.html
django_tracking_analyzer-1.1.1.dist-info/LICENSE
django_tracking_analyzer-1.1.1.dist-info/METADATA
django_tracking_analyzer-1.1.1.dist-info/WHEEL
django_tracking_analyzer-1.1.1.dist-info/top_level.txt
django_tracking_analyzer-1.1.1.dist-info/RECORD
