Metadata-Version: 1.1
Name: django-tracking-analyzer
Version: 1.1.1
Summary: User actions tracking and analytics for Django sites.
Home-page: https://github.com/jose-lpa/django-tracking-analyzer
Author: José Luis Patiño Andrés
Author-email: jose.lpa@gmail.com
License: UNKNOWN
Keywords: django,analytics,web,monitoring,logging
Platform: UNKNOWN
Classifier: Development Status :: 5 - Production/Stable
Classifier: Framework :: Django :: 2.1
Classifier: Framework :: Django :: 2.2
Classifier: Framework :: Django :: 3.0
Classifier: Intended Audience :: Developers
Classifier: License :: OSI Approved :: GNU General Public License v3 (GPLv3)
Classifier: Operating System :: Unix
Classifier: Operating System :: MacOS
Classifier: Operating System :: Microsoft :: Windows
Classifier: Programming Language :: Python :: 3.5
Classifier: Programming Language :: Python :: 3.6
Classifier: Programming Language :: Python :: 3.7
Classifier: Programming Language :: Python :: 3.8
Classifier: Topic :: Software Development :: Libraries :: Application Frameworks
Classifier: Topic :: System :: Logging
Classifier: Topic :: System :: Monitoring
Classifier: Topic :: Utilities
